eenum.py
eenum-0.10.0.dist-info/DESCRIPTION.rst
eenum-0.10.0.dist-info/METADATA
eenum-0.10.0.dist-info/RECORD
eenum-0.10.0.dist-info/WHEEL
eenum-0.10.0.dist-info/metadata.json
eenum-0.10.0.dist-info/top_level.txt
